youtube_unlimited_api/__init__.py
youtube_unlimited_api/youtube_unlimited_api.py
youtube_unlimited_api-0.1.dist-info/METADATA
youtube_unlimited_api-0.1.dist-info/WHEEL
youtube_unlimited_api-0.1.dist-info/top_level.txt
youtube_unlimited_api-0.1.dist-info/RECORD
