Metadata-Version: 2.1
Name: youtube-unlimited-api
Version: 0.1
Requires-Dist: requests
